setup.py
kfactor/__init__.py
kfactor.egg-info/PKG-INFO
kfactor.egg-info/SOURCES.txt
kfactor.egg-info/dependency_links.txt
kfactor.egg-info/not-zip-safe
kfactor.egg-info/requires.txt
kfactor.egg-info/top_level.txt