Metadata-Version: 1.2
Name: kfactor
Version: 0.2.0
Summary: deprecated
Home-page: http://github.com/ulf1/scipy-psdm
Author: Ulf Hamster
Author-email: 554c46@gmail.com
License: MIT
Platform: UNKNOWN
Requires-Python: >=3.6
